pdfminer/__init__.py
pdfminer/_saslprep.py
pdfminer/arcfour.py
pdfminer/ascii85.py
pdfminer/casting.py
pdfminer/ccitt.py
pdfminer/cmapdb.py
pdfminer/converter.py
pdfminer/data_structures.py
pdfminer/encodingdb.py
pdfminer/fontmetrics.py
pdfminer/glyphlist.py
pdfminer/high_level.py
pdfminer/image.py
pdfminer/jbig2.py
pdfminer/latin_enc.py
pdfminer/layout.py
pdfminer/lzw.py
pdfminer/pdfcolor.py
pdfminer/pdfdevice.py
pdfminer/pdfdocument.py
pdfminer/pdfexceptions.py
pdfminer/pdffont.py
pdfminer/pdfinterp.py
pdfminer/pdfpage.py
pdfminer/pdfparser.py
pdfminer/pdftypes.py
pdfminer/psexceptions.py
pdfminer/psparser.py
pdfminer/py.typed
pdfminer/runlength.py
pdfminer/settings.py
pdfminer/utils.py
pdfminer/cmap/78-EUC-H.pickle.gz
pdfminer/cmap/78-EUC-V.pickle.gz
pdfminer/cmap/78-H.pickle.gz
pdfminer/cmap/78-RKSJ-H.pickle.gz
pdfminer/cmap/78-RKSJ-V.pickle.gz
pdfminer/cmap/78-V.pickle.gz
pdfminer/cmap/78ms-RKSJ-H.pickle.gz
pdfminer/cmap/78ms-RKSJ-V.pickle.gz
pdfminer/cmap/83pv-RKSJ-H.pickle.gz
pdfminer/cmap/83pv-RKSJ-V.pickle.gz
pdfminer/cmap/90ms-RKSJ-H.pickle.gz
pdfminer/cmap/90ms-RKSJ-V.pickle.gz
pdfminer/cmap/90msp-RKSJ-H.pickle.gz
pdfminer/cmap/90msp-RKSJ-V.pickle.gz
pdfminer/cmap/90pv-RKSJ-H.pickle.gz
pdfminer/cmap/90pv-RKSJ-V.pickle.gz
pdfminer/cmap/Add-H.pickle.gz
pdfminer/cmap/Add-RKSJ-H.pickle.gz
pdfminer/cmap/Add-RKSJ-V.pickle.gz
pdfminer/cmap/Add-V.pickle.gz
pdfminer/cmap/B5-H.pickle.gz
pdfminer/cmap/B5-V.pickle.gz
pdfminer/cmap/B5pc-H.pickle.gz
pdfminer/cmap/B5pc-V.pickle.gz
pdfminer/cmap/CNS-EUC-H.pickle.gz
pdfminer/cmap/CNS-EUC-V.pickle.gz
pdfminer/cmap/CNS1-H.pickle.gz
pdfminer/cmap/CNS1-V.pickle.gz
pdfminer/cmap/CNS2-H.pickle.gz
pdfminer/cmap/CNS2-V.pickle.gz
pdfminer/cmap/ETHK-B5-H.pickle.gz
pdfminer/cmap/ETHK-B5-V.pickle.gz
pdfminer/cmap/ETen-B5-H.pickle.gz
pdfminer/cmap/ETen-B5-V.pickle.gz
pdfminer/cmap/ETenms-B5-H.pickle.gz
pdfminer/cmap/ETenms-B5-V.pickle.gz
pdfminer/cmap/EUC-H.pickle.gz
pdfminer/cmap/EUC-V.pickle.gz
pdfminer/cmap/Ext-H.pickle.gz
pdfminer.bc-0.0.2.dist-info/LICENSE
pdfminer.bc-0.0.2.dist-info/METADATA
pdfminer.bc-0.0.2.dist-info/WHEEL
pdfminer.bc-0.0.2.dist-info/top_level.txt
pdfminer.bc-0.0.2.dist-info/RECORD
